best_package/__init__.py
best_package/best_package_engine.py
best_package/d00_data_access/data_access.py
best_package/d00_data_access/datasets/dataset01_dataset/__init__.py
best_package/d00_data_access/datasets/dataset01_dataset/checksums.tsv
best_package/d00_data_access/datasets/dataset01_dataset/dataset01_dataset.py
best_package/d00_data_access/datasets/dataset01_dataset/dataset01_dataset_test.py
best_package/d00_data_access/datasets/dataset01_dataset/dummy_data/TODO-add_fake_data_in_this_directory.txt
best_package/d00_data_access/model/contextmodel.py
best_package/d00_data_access/model/datamodel.py
best_package/d00_data_access/services/data_getters.py
best_package/d00_data_access/services/data_savers.py
best_package/d00_data_access/services/initialise_srv.py
best_package/d00_data_access/services/spartan_mrc_data_sync_srv.py
best_package/d01_pre_processing/model/contextmodel.py
best_package/d01_pre_processing/pre_processor.py
best_package/d01_pre_processing/services/finalizing_srv.py
best_package/d01_pre_processing/services/initialise_srv.py
best_package/d01_pre_processing/services/null_strategy_srv.py
best_package/d01_pre_processing/services/prepare_data_for_modelling.py
best_package/d02_modelling/model/contextmodel.py
best_package/d02_modelling/model/hyper_parameters.py
best_package/d02_modelling/model/my_model.py
best_package/d02_modelling/model/my_trainer.py
best_package/d02_modelling/modeller.py
best_package/d02_modelling/services/deeplearning_srv.py
best_package/d02_modelling/services/finalizing_srv.py
best_package/d02_modelling/services/initialise_srv.py
best_package/d03_outputting/model/contextmodel.py
best_package/d03_outputting/outputter.py
best_package/d03_outputting/services/finalizing_srv.py
best_package/d03_outputting/services/initialise_srv.py
best_package/d_utils/cleaners.py
best_package/d_utils/config_controller.py
best_package/d_utils/constants.py
best_package/d_utils/data_browser.py
best_package/d_utils/enums.py
best_package-0.1.1.dist-info/WHEEL
best_package-0.1.1.dist-info/METADATA
best_package-0.1.1.dist-info/RECORD
