Metadata-Version: 2.1
Name: best-package
Version: 0.1.1
Summary: 
Author: Zaher Joukhadar
Author-email: zaher@joukhadar.me
Requires-Python: >=3.8,<3.11
Classifier: Programming Language :: Python :: 3
Classifier: Programming Language :: Python :: 3.8
Classifier: Programming Language :: Python :: 3.9
Requires-Dist: PyYAML (>=6.0,<7.0)
Requires-Dist: colored (>=1.4.3,<2.0.0)
Requires-Dist: flax (>=0.6.0,<0.7.0)
Requires-Dist: ipython (>=8.5.0,<9.0.0)
Requires-Dist: ml-collections (>=0.1.1,<0.2.0)
Requires-Dist: nbformat (>=5.4.0,<6.0.0)
Requires-Dist: notebook (>=6.4.12,<7.0.0)
Requires-Dist: optax (>=0.1.3,<0.2.0)
Requires-Dist: pandas (>=1.4.4,<2.0.0)
Requires-Dist: pyfiglet (>=0.8.post1,<0.9)
Requires-Dist: tensorflow (>=2.10.0,<3.0.0)
Requires-Dist: tensorflow-datasets (>=4.6.0,<5.0.0)
Requires-Dist: tqdm (>=4.64.1,<5.0.0)
